gfFermentation/__init__.py
gfFermentation/controller.py
gfFermentation/grainfather.py
gfFermentation-0.0.5.dist-info/LICENSE
gfFermentation-0.0.5.dist-info/METADATA
gfFermentation-0.0.5.dist-info/WHEEL
gfFermentation-0.0.5.dist-info/top_level.txt
gfFermentation-0.0.5.dist-info/RECORD
