Metadata-Version: 2.1
Name: gfFermentation
Version: 0.0.5
Summary: Connect and control the Grainfather conical fermenter and other controlers
Home-page: https://github.com/wardsimon/gfFermentation/
Author: simonward
Author-email: 
License: BSD3
Platform: UNKNOWN
License-File: LICENSE
Requires-Dist: requests
